[{"reserved":true,"priceClass":"b","seat":"4a","myid":"77bcf8cdbf1"},{"reserved":true,"priceClass":"b","seat":"4b","myid":"7bcf8cdbf18"},{"reserved":false,"priceClass":"b","seat":"4c"},{"reserved":false,"priceClass":"b","seat":"4d"},{"reserved":true,"priceClass":"b","seat":"4e","myid":"c13c5deff74"},{"reserved":false,"priceClass":"b","seat":"4f"},{"reserved":false,"priceClass":"b","seat":"3a"},{"reserved":false,"priceClass":"b","seat":"3b"},{"reserved":false,"priceClass":"b","seat":"3c"},{"reserved":true,"priceClass":"b","seat":"3d","myid":"66c65a01e21"},{"reserved":false,"priceClass":"b","seat":"3e"},{"reserved":false,"priceClass":"b","seat":"3f"},{"reserved":false,"priceClass":"a","seat":"2a"},{"reserved":false,"priceClass":"a","seat":"2b"},{"reserved":false,"priceClass":"a","seat":"2c"},{"reserved":false,"priceClass":"a","seat":"2d"},{"reserved":false,"priceClass":"a","seat":"2e"},{"reserved":false,"priceClass":"a","seat":"2f"},{"reserved":false,"priceClass":"a","seat":"1a"},{"reserved":false,"priceClass":"a","seat":"1b"},{"reserved":false,"priceClass":"a","seat":"1c"},{"reserved":false,"priceClass":"a","seat":"1d"},{"reserved":false,"priceClass":"a","seat":"1e"},{"reserved":false,"priceClass":"a","seat":"1f"}]